LICENCE
openscm_calibration-0.6.1.dist-info/METADATA
openscm_calibration-0.6.1.dist-info/WHEEL
openscm_calibration-0.6.1.dist-info/licenses/LICENCE
openscm_calibration/__init__.py
openscm_calibration/calibration_demo.py
openscm_calibration/cost/__init__.py
openscm_calibration/cost/scmdata.py
openscm_calibration/emcee_plotting.py
openscm_calibration/emcee_utils.py
openscm_calibration/exceptions.py
openscm_calibration/matplotlib_utils.py
openscm_calibration/minimize.py
openscm_calibration/model_runner.py
openscm_calibration/parameter_handling.py
openscm_calibration/py.typed
openscm_calibration/scipy_plotting/__init__.py
openscm_calibration/scipy_plotting/base.py
openscm_calibration/scipy_plotting/scmdata.py
openscm_calibration/scmdata_utils.py
openscm_calibration/store/__init__.py
openscm_calibration/store/base.py
openscm_calibration/store/scmdata.py
openscm_calibration/typing.py
openscm_calibration-0.6.1.dist-info/RECORD
