Metadata-Version: 2.1
Name: openscm-calibration
Version: 0.6.1
Summary: Calibration tools for simple climate models (with potential for applications elsewhere)
Author-Email: Zebedee Nicholls <zebedee.nicholls@climate-energy-college.org>
License: BSD-3-Clause
Classifier: License :: OSI Approved :: BSD License
Requires-Python: >=3.9
Requires-Dist: attrs
Requires-Dist: more-itertools
Requires-Dist: numpy
Requires-Dist: pint
Requires-Dist: typing-extensions
Requires-Dist: corner~=2.0; extra == "plots"
Requires-Dist: ipython~=8.18; extra == "plots"
Requires-Dist: matplotlib~=3.7; extra == "plots"
Requires-Dist: pandas~=2.2; extra == "plots"
Requires-Dist: seaborn~=0.13; extra == "plots"
Requires-Dist: scmdata~=0.17; extra == "scmdata"
Requires-Dist: appdirs==1.4.4; extra == "locked"
Requires-Dist: attrs==24.2.0; extra == "locked"
Requires-Dist: flexcache==0.3; extra == "locked"
Requires-Dist: flexparser==0.3.1; extra == "locked"
Requires-Dist: more-itertools==10.5.0; extra == "locked"
Requires-Dist: numpy==2.0.2; extra == "locked"
Requires-Dist: pint==0.24.3; extra == "locked"
Requires-Dist: typing-extensions==4.12.2; extra == "locked"
Requires-Dist: asttokens==2.4.1; extra == "plots-locked"
Requires-Dist: colorama==0.4.6; extra == "plots-locked"
Requires-Dist: contourpy==1.3.0; extra == "plots-locked"
Requires-Dist: corner==2.2.2; extra == "plots-locked"
Requires-Dist: cycler==0.12.1; extra == "plots-locked"
Requires-Dist: decorator==5.1.1; extra == "plots-locked"
Requires-Dist: exceptiongroup==1.2.2; python_version < "3.11" and extra == "plots-locked"
Requires-Dist: executing==2.1.0; extra == "plots-locked"
Requires-Dist: fonttools==4.53.1; extra == "plots-locked"
Requires-Dist: importlib-resources==6.4.5; python_version < "3.10" and extra == "plots-locked"
Requires-Dist: ipython==8.18.1; extra == "plots-locked"
Requires-Dist: jedi==0.19.1; extra == "plots-locked"
Requires-Dist: kiwisolver==1.4.7; extra == "plots-locked"
Requires-Dist: matplotlib==3.9.2; extra == "plots-locked"
Requires-Dist: matplotlib-inline==0.1.7; extra == "plots-locked"
Requires-Dist: numpy==2.0.2; extra == "plots-locked"
Requires-Dist: packaging==24.1; extra == "plots-locked"
Requires-Dist: pandas==2.2.2; extra == "plots-locked"
Requires-Dist: parso==0.8.4; extra == "plots-locked"
Requires-Dist: pexpect==4.9.0; sys_platform != "win32" and extra == "plots-locked"
Requires-Dist: pillow==10.4.0; extra == "plots-locked"
Requires-Dist: prompt-toolkit==3.0.47; extra == "plots-locked"
Requires-Dist: ptyprocess==0.7.0; (sys_platform != "win32" or os_name != "nt") and extra == "plots-locked"
Requires-Dist: pure-eval==0.2.3; extra == "plots-locked"
Requires-Dist: pygments==2.18.0; extra == "plots-locked"
Requires-Dist: pyparsing==3.1.4; extra == "plots-locked"
Requires-Dist: python-dateutil==2.9.0.post0; extra == "plots-locked"
Requires-Dist: pytz==2024.2; extra == "plots-locked"
Requires-Dist: seaborn==0.13.2; extra == "plots-locked"
Requires-Dist: six==1.16.0; extra == "plots-locked"
Requires-Dist: stack-data==0.6.3; extra == "plots-locked"
Requires-Dist: traitlets==5.14.3; extra == "plots-locked"
Requires-Dist: typing-extensions==4.12.2; extra == "plots-locked"
Requires-Dist: tzdata==2024.1; extra == "plots-locked"
Requires-Dist: wcwidth==0.2.13; extra == "plots-locked"
Requires-Dist: zipp==3.20.2; python_version < "3.10" and extra == "plots-locked"
Requires-Dist: appdirs==1.4.4; extra == "scmdata-locked"
Requires-Dist: cftime==1.6.4; extra == "scmdata-locked"
Requires-Dist: colorama==0.4.6; extra == "scmdata-locked"
Requires-Dist: flexcache==0.3; extra == "scmdata-locked"
Requires-Dist: flexparser==0.3.1; extra == "scmdata-locked"
Requires-Dist: globalwarmingpotentials==0.11.1; extra == "scmdata-locked"
Requires-Dist: numpy==2.0.2; extra == "scmdata-locked"
Requires-Dist: openscm-units==0.6.1; extra == "scmdata-locked"
Requires-Dist: packaging==24.1; extra == "scmdata-locked"
Requires-Dist: pandas==2.2.2; extra == "scmdata-locked"
Requires-Dist: pint==0.24.3; extra == "scmdata-locked"
Requires-Dist: pint-pandas==0.6.2; extra == "scmdata-locked"
Requires-Dist: python-dateutil==2.9.0.post0; extra == "scmdata-locked"
Requires-Dist: pytz==2024.2; extra == "scmdata-locked"
Requires-Dist: scmdata==0.17.0; extra == "scmdata-locked"
Requires-Dist: six==1.16.0; extra == "scmdata-locked"
Requires-Dist: tqdm==4.66.5; extra == "scmdata-locked"
Requires-Dist: typing-extensions==4.12.2; extra == "scmdata-locked"
Requires-Dist: tzdata==2024.1; extra == "scmdata-locked"
Requires-Dist: xarray==2024.7.0; extra == "scmdata-locked"
Provides-Extra: plots
Provides-Extra: scmdata
Provides-Extra: locked
Provides-Extra: plots-locked
Provides-Extra: scmdata-locked
